rl_zoo3/__init__.py
rl_zoo3/benchmark.py
rl_zoo3/callbacks.py
rl_zoo3/cli.py
rl_zoo3/enjoy.py
rl_zoo3/exp_manager.py
rl_zoo3/gym_patches.py
rl_zoo3/hyperparams_opt.py
rl_zoo3/import_envs.py
rl_zoo3/load_from_hub.py
rl_zoo3/push_to_hub.py
rl_zoo3/py.typed
rl_zoo3/record_training.py
rl_zoo3/record_video.py
rl_zoo3/train.py
rl_zoo3/utils.py
rl_zoo3/version.txt
rl_zoo3/wrappers.py
rl_zoo3/hyperparams/a2c.yml
rl_zoo3/hyperparams/ars.yml
rl_zoo3/hyperparams/crossq.yml
rl_zoo3/hyperparams/ddpg.yml
rl_zoo3/hyperparams/dqn.yml
rl_zoo3/hyperparams/her.yml
rl_zoo3/hyperparams/ppo.yml
rl_zoo3/hyperparams/ppo_lstm.yml
rl_zoo3/hyperparams/qrdqn.yml
rl_zoo3/hyperparams/sac.yml
rl_zoo3/hyperparams/td3.yml
rl_zoo3/hyperparams/tqc.yml
rl_zoo3/hyperparams/trpo.yml
rl_zoo3/plots/__init__.py
rl_zoo3/plots/all_plots.py
rl_zoo3/plots/plot_from_file.py
rl_zoo3/plots/plot_train.py
rl_zoo3/plots/score_normalization.py
rl_zoo3-2.7.0.dist-info/licenses/LICENSE
rl_zoo3-2.7.0.dist-info/METADATA
rl_zoo3-2.7.0.dist-info/WHEEL
rl_zoo3-2.7.0.dist-info/entry_points.txt
rl_zoo3-2.7.0.dist-info/top_level.txt
rl_zoo3-2.7.0.dist-info/RECORD
